MANIFEST.in
README.md
setup.py
test/__init__.py
test/test_builder.py
test/test_feedparser.py
test/test_fetcher.py
zenfeed/__init__.py
zenfeed/actor.py
zenfeed/app.py
zenfeed/builder.py
zenfeed/caching.py
zenfeed/deadline_manager.py
zenfeed/fetcher.py
zenfeed/log.py
zenfeed/migrations.py
zenfeed/models.py
zenfeed/settings.py
zenfeed/start.py
zenfeed/views.py
zenfeed/workers.py
zenfeed.egg-info/PKG-INFO
zenfeed.egg-info/SOURCES.txt
zenfeed.egg-info/dependency_links.txt
zenfeed.egg-info/entry_points.txt
zenfeed.egg-info/not-zip-safe
zenfeed.egg-info/requires.txt
zenfeed.egg-info/top_level.txt
zenfeed/static/css/grid.css
zenfeed/static/css/indieflower.woff
zenfeed/static/css/style.css
zenfeed/static/html/add_feed.html
zenfeed/static/html/config.html
zenfeed/static/html/edit_feed.html
zenfeed/static/html/feed.html
zenfeed/static/img/feedicon.png
zenfeed/static/img/feedicon.svg
zenfeed/static/img/zenicon.png
zenfeed/static/img/zenicon.svg
zenfeed/static/js/zenfeed.js
zenfeed/static/js/admin/controllers.js
zenfeed/static/js/admin/routes.js
zenfeed/static/js/admin/services.js
zenfeed/static/js/admin/translations.js
zenfeed/templates/admin.html
zenfeed/templates/base.html
zenfeed/templates/entry.html
zenfeed/templates/feed.html
zenfeed/templates/feeds.html
zenfeed/templates/login.html
zenfeed/translations/en/LC_MESSAGES/messages.mo
zenfeed/translations/es/LC_MESSAGES/messages.mo