Metadata-Version: 1.0
Name: zenfeed
Version: 0.4.0
Summary: Zen RSS feed reader.
Home-page: http://github.com/fspot/zenfeed
Author: fspot
Author-email: fred@fspot.org
License: BSD
Platform: UNKNOWN
